license_seeker/1.txt
license_seeker/Copy (1) 1.txt
license_seeker/__init__.py
license_seeker/apis/__init__.py
license_seeker/apis/connection_config.py
license_seeker/apis/converters/__init__.py
license_seeker/apis/converters/converter.py
license_seeker/apis/converters/github_converter.py
license_seeker/apis/converters/pypi_converter.py
license_seeker/apis/parsers/__init__.py
license_seeker/apis/parsers/github_parser.py
license_seeker/apis/parsers/parser.py
license_seeker/apis/parsers/pypi_parser.py
license_seeker/apis/receiver.py
license_seeker/lic.txt
license_seeker/main.py
license_seeker-0.3.1.dist-info/METADATA
license_seeker-0.3.1.dist-info/WHEEL
license_seeker-0.3.1.dist-info/COPYING
license_seeker-0.3.1.dist-info/entry_points.txt
license_seeker-0.3.1.dist-info/RECORD
