Metadata-Version: 2.1
Name: license-seeker
Version: 0.3.1
Summary: 
Home-page: https://gitlab.com/KKlochko/license-seeker
License: GPL-3.0-or-later
Author: KKlochko
Author-email: kostya_klochko@ukr.net
Requires-Python: >=3.10,<4.0
Classifier: License :: OSI Approved :: GNU General Public License v3 or later (GPLv3+)
Classifier: Programming Language :: Python :: 3
Classifier: Programming Language :: Python :: 3.10
Classifier: Programming Language :: Python :: 3.11
Requires-Dist: requests (>=2.28.2,<3.0.0)
Project-URL: Bug Tracker, https://gitlab.com/KKlochko/license-seeker/issues
Project-URL: Repository, https://gitlab.com/KKlochko/license-seeker
